sko/ACA.py
sko/AFSA.py
sko/DE.py
sko/GA.py
sko/IA.py
sko/PSO.py
sko/SA.py
sko/__init__.py
sko/base.py
sko/demo_func.py
sko/tool_kit.py
sko/tools.py
sko/operators/__init__.py
sko/operators/crossover.py
sko/operators/mutation.py
sko/operators/ranking.py
sko/operators/selection.py
sko/operators_gpu/__init__.py
sko/operators_gpu/crossover_gpu.py
sko/operators_gpu/mutation_gpu.py
sko/operators_gpu/ranking_gpu.py
sko/operators_gpu/selection_gpu.py
tests/__init__.py
tests/test_demo_func.py
tests/test_x2gray.py
scikit_opt-0.6.6.dist-info/LICENSE
scikit_opt-0.6.6.dist-info/METADATA
scikit_opt-0.6.6.dist-info/WHEEL
scikit_opt-0.6.6.dist-info/top_level.txt
scikit_opt-0.6.6.dist-info/RECORD
