Metadata-Version: 2.1
Name: scikit-opt
Version: 0.6.6
Summary: Swarm Intelligence in Python
Home-page: https://github.com/guofei9987/scikit-opt
Author: Guo Fei
Author-email: guofei9987@foxmail.com
License: MIT
Platform: linux
Platform: windows
Platform: macos
Requires-Python: >=3.5
